LICENSE.txt
README.md
setup.cfg
setup.py
ngcaged/__init__.py
ngcaged/ngcaged.py
ngcaged.egg-info/PKG-INFO
ngcaged.egg-info/SOURCES.txt
ngcaged.egg-info/dependency_links.txt
ngcaged.egg-info/top_level.txt