Metadata-Version: 2.1
Name: ngcaged
Version: 1.0.0
Summary: Dados do NOVO CAGED
Home-page: UNKNOWN
Author: Guilherme Nogueira
Author-email: guilherme.info.nog@aluno.ufsj.edu.br
License: MIT
Keywords: novo caged
Platform: UNKNOWN
Classifier: Development Status :: 5 - Production/Stable
Classifier: Intended Audience :: Developers
Classifier: License :: OSI Approved :: MIT License
Classifier: Natural Language :: Portuguese (Brazilian)
Classifier: Operating System :: Microsoft :: Windows :: Windows 10 
Classifier: Topic :: Software Development :: Internationalization
Classifier: Topic :: Scientific/Engineering :: Physics
License-File: LICENSE.txt
